argklass/__init__.py
argklass/argformat.py
argklass/arguments.py
argklass/cache.py
argklass/cli.py
argklass/command.py
argklass/config.py
argklass/docstring.py
argklass/groupargs.py
argklass/parallel.py
argklass/plugin.py
argklass-1.4.4.dist-info/LICENSE
argklass-1.4.4.dist-info/METADATA
argklass-1.4.4.dist-info/WHEEL
argklass-1.4.4.dist-info/top_level.txt
argklass-1.4.4.dist-info/RECORD
