Metadata-Version: 2.1
Name: argklass
Version: 1.4.4
Summary: Argparse generator from dataclass
Home-page: https://argklass.readthedocs.io
Author: Delaunay
Author-email: pierre@delaunay.io
License: BSD 3-Clause License
Classifier: License :: OSI Approved :: BSD License
Classifier: Programming Language :: Python :: 3.8
Classifier: Programming Language :: Python :: 3.9
Classifier: Programming Language :: Python :: 3.10
Classifier: Operating System :: OS Independent
License-File: LICENSE
Requires-Dist: importlib-resources
Requires-Dist: hjson
Provides-Extra: all
Requires-Dist: importlib-resources ; extra == 'all'
Provides-Extra: plugins
Requires-Dist: importlib-resources ; extra == 'plugins'
